{"accounts":[{"account":{"active":false,"allocationHistory":[],"balance":"0","identity":{"address":"N\u0000sourcecred\u0000core\u0000IDENTITY\u0000xIYqrgSL5HXRAN4kPam1kg\u0000","aliases":[{"address":"N\u0000sourcecred\u0000discord\u0000MEMBER\u0000user\u0000694274491819491389\u0000","description":"discord/Filipe---TH-0#1672"}],"id":"xIYqrgSL5HXRAN4kPam1kg","name":"Filipe---TH-0","subtype":"USER"},"mergedIdentityIds":["xIYqrgSL5HXRAN4kPam1kg"],"paid":"0","payoutAddresses":{}},"cred":[0.047933878088890845],"totalCred":0.047933878088890845},{"account":{"active":false,"allocationHistory":[],"balance":"0","identity":{"address":"N\u0000sourcecred\u0000core\u0000IDENTITY\u0000jrYVk0oVzI7IxDXEnuEBTA\u0000","aliases":[{"address":"N\u0000sourcecred\u0000discord\u0000MEMBER\u0000user\u0000751050080466894921\u0000","description":"discord/Sarah---TH-0#9971"}],"id":"jrYVk0oVzI7IxDXEnuEBTA","name":"Sarah---TH-0","subtype":"USER"},"mergedIdentityIds":["jrYVk0oVzI7IxDXEnuEBTA"],"paid":"0","payoutAddresses":{}},"cred":[0.9520657186562643],"totalCred":0.9520657186562643},{"account":{"active":false,"allocationHistory":[],"balance":"0","identity":{"address":"N\u0000sourcecred\u0000core\u0000IDENTITY\u0000No8k54j1kyN9W0rlPEM5RA\u0000","aliases":[{"address":"N\u0000sourcecred\u0000discord\u0000MEMBER\u0000bot\u0000928673671428599838\u0000","description":"discord/Source-Token-TestBot#0483"}],"id":"No8k54j1kyN9W0rlPEM5RA","name":"Source-Token-TestBot","subtype":"BOT"},"mergedIdentityIds":["No8k54j1kyN9W0rlPEM5RA"],"paid":"0","payoutAddresses":{}},"cred":[7.377612310880153e-39],"totalCred":7.377612310880153e-39},{"account":{"active":false,"allocationHistory":[],"balance":"0","identity":{"address":"N\u0000sourcecred\u0000core\u0000IDENTITY\u00005aKZG5QuqkaQodJBhYDMFA\u0000","aliases":[{"address":"N\u0000sourcecred\u0000discord\u0000MEMBER\u0000bot\u0000928722686388088852\u0000","description":"discord/Pollen-Token#7258"}],"id":"5aKZG5QuqkaQodJBhYDMFA","name":"Pollen-Token","subtype":"BOT"},"mergedIdentityIds":["5aKZG5QuqkaQodJBhYDMFA"],"paid":"0","payoutAddresses":{}},"cred":[7.377612310880153e-39],"totalCred":7.377612310880153e-39},{"account":{"active":true,"allocationHistory":[],"balance":"0","identity":{"address":"N\u0000sourcecred\u0000core\u0000IDENTITY\u0000kJWTl9QOfOoin9WIgjF8ew\u0000","aliases":[],"id":"kJWTl9QOfOoin9WIgjF8ew","name":"SourceCred","subtype":"PROJECT"},"mergedIdentityIds":["kJWTl9QOfOoin9WIgjF8ew"],"paid":"0","payoutAddresses":{}},"cred":[7.377612310880153e-39],"totalCred":7.377612310880153e-39}],"intervals":[{"endTimeMs":1641686400000,"startTimeMs":1641081600000}],"unclaimedAliases":[]}